test0313/__init__.py
test0313/eda.py
test0313/eda_simple.py
test0313/plot.py
test0313/process.py
test0313/txt2pkl.py
test0313-0.0.0.4.dist-info/METADATA
test0313-0.0.0.4.dist-info/WHEEL
test0313-0.0.0.4.dist-info/top_level.txt
test0313-0.0.0.4.dist-info/RECORD
